s3_manager_package_nci_23384069/__init__.py
s3_manager_package_nci_23384069/s3_manager.py
s3_manager_package_nci_23384069-1.0.1.dist-info/METADATA
s3_manager_package_nci_23384069-1.0.1.dist-info/WHEEL
s3_manager_package_nci_23384069-1.0.1.dist-info/licenses/LICENSE
s3_manager_package_nci_23384069-1.0.1.dist-info/RECORD
