Metadata-Version: 2.3
Name: s3_manager_package_nci_23384069
Version: 1.0.1
Summary: An AWS s3 utility package
Project-URL: Homepage, https://github.com/Ughanze23/CPP-PROJECT/tree/main/s3_manager
Author-email: Ikenna Ughanze <ughanzepolycarp@gmail.com>
License-File: LICENSE
Classifier: License :: OSI Approved :: MIT License
Classifier: Operating System :: OS Independent
Classifier: Programming Language :: Python :: 3
Requires-Python: >=3.8
